seqabpy/__init__.py
seqabpy/gatsby.py
seqabpy/gavi.py
seqabpy-0.2.2.dist-info/METADATA
seqabpy-0.2.2.dist-info/WHEEL
seqabpy-0.2.2.dist-info/licenses/LICENSE
seqabpy-0.2.2.dist-info/RECORD
