Metadata-Version: 2.4
Name: seqabpy
Version: 0.2.2
Summary: Sequential A/B Testing Framework in Python
Project-URL: Homepage, https://npodlozhniy.github.io/posts/sequential-testing/
Project-URL: Source Code, https://github.com/NPodlozhniy/seqabpy
Author-email: Nikita Podlozhniy <podlozhnyy.ne@phystech.edu>
License-Expression: Apache-2.0
License-File: LICENSE
Keywords: AB,AVI,GST,Sequential,Testing
Classifier: License :: OSI Approved :: Apache Software License
Classifier: Operating System :: OS Independent
Classifier: Programming Language :: Python :: 3
Requires-Python: >=3.7
Requires-Dist: numpy
Requires-Dist: scipy
Requires-Dist: statsmodels
